quickbin/binning.h
quickbin/iterators.c
quickbin/api_helpers.h
quickbin/iterators.h
quickbin/binning.c
quickbin/definitions.py
quickbin/__init__.py
quickbin/_quickbin_core.c
quickbin/base.py
quickbin/_quickbin_core.pyi
quickbin/_quickbin_core.cpython-312-x86_64-linux-musl.so
quickbin/_binning_handlers.py
quickbin/benchmarks/__init__.py
quickbin/benchmarks/memlogger.py
quickbin/benchmarks/benchmark.py
quickbin/tests/test_outputs.py
quickbin/tests/test_reference_leaks.py
quickbin/tests/test_errors.py
quickbin/tests/refalarm.py
quickbin/tests/__init__.py
quickbin/tests/_quickbin_test_utils.pyi
quickbin/tests/_quickbin_test_utils.cpython-312-x86_64-linux-musl.so
quickbin/tests/_quickbin_test_utils.c
quickbin-0.2.0.dist-info/METADATA
quickbin-0.2.0.dist-info/RECORD
quickbin-0.2.0.dist-info/top_level.txt
quickbin-0.2.0.dist-info/WHEEL
quickbin-0.2.0.dist-info/LICENSE.md
