Metadata-Version: 2.2
Name: quickbin
Version: 0.2.0
Summary: fast generalized histogram function
Author-email: "Michael St. Clair" <mstclair@millionconcepts.com>, Zack Weinberg <zack@millionconcepts.com>
License: ###  BSD 3-Clause License
Project-URL: Repository, https://github.com/MillionConcepts/quickbin
Classifier: Development Status :: 4 - Beta
Classifier: License :: OSI Approved :: BSD License
Classifier: Operating System :: OS Independent
Classifier: Programming Language :: Python :: 3
Requires-Python: >=3.11
License-File: LICENSE.md
Requires-Dist: numpy
Provides-Extra: tests
Requires-Dist: pytest; extra == "tests"
Provides-Extra: benchmark
Requires-Dist: psutil; extra == "benchmark"
Requires-Dist: scipy; extra == "benchmark"
